LICENSE
MANIFEST.in
README.md
setup.py
tests/test_tests.py
xenv/__init__.py
xenv/__main__.py
xenv/__version__
xenv/yq.py
xenv/scripts/launch.zsh
xenv/scripts/pre_load.zsh
xenv_plugin/base/__init__.py
xenvironment.egg-info/PKG-INFO
xenvironment.egg-info/SOURCES.txt
xenvironment.egg-info/dependency_links.txt
xenvironment.egg-info/entry_points.txt
xenvironment.egg-info/not-zip-safe
xenvironment.egg-info/requires.txt
xenvironment.egg-info/top_level.txt